[
  {
    "id": "1",
    "title": "Mataji’s Havan 2026 – Chaitri Navratri Celebration",
    "date": "28th March, 2026 - Saturday - 1:30PM ET to 8PM ET",
    "startDateISO": "2026-03-28T13:30:00-04:00",
    "endDateISO": "2026-03-28T20:00:00-04:00",
    "location": "Hindu Heritage Center (6300 Missisauga Road), Mississauga",
    "description": "Chaitri Navratri marks the beginning of the Hindu New Year and is dedicated to Goddess Durga. This special Mataji’s Havan is a spiritual gathering to seek the blessings of Maa Limbach, with traditional havan, limited Sah-Yajmaan seva , opportunities for Ahuti participation, and Maha-Prasad served after Aarti.",
    "imageUrl": "/events/havan.jpg",
    "upcoming": true
  },
  {
    "id": "2",
    "title": "Community Picnic & Family Day",
    "date": "To be announced(July 2026)",
    "location": "To be announced",
    "description": "A relaxed outdoor gathering in July 2026 for families and friends to enjoy games, traditional sports, team activities, and delicious picnic-style food. A perfect opportunity to connect, celebrate, and create lasting memories together. Exact date and venue will be announced closer to the event.",
    "imageUrl": "/events/community-picnic.jpg",
    "upcoming": true
  },
  {
    "id": "3",
    "title": "Diwali 2026 Celebration",
    "date": "To be announced(November 2026)",
    "location": "To be announced",
    "description": "An annual Diwali celebration bringing families, friends, and generations together to celebrate light, hope, and new beginnings. This event will include cultural programs and shared festive moments. Exact date and venue for Diwali 2026 will be announced closer to the festival.",
    "imageUrl": "",
    "upcoming": true
  },
  {
    "id": "4",
    "title": "Get together",
    "date": "18th Dec, 2010",
    "location": "Hindu Heritage Center, Mississauga",
    "description": "",
    "imageUrl": "",
    "upcoming": false
  },
  {
    "id": "5",
    "title": "Samaj Picnic",
    "date": "12th Dec, 2012",
    "location": "Patticoat Park",
    "description": "",
    "imageUrl": "",
    "upcoming": false
  },
  {
    "id": "6",
    "title": "Limbach Samaj Picnic",
    "date": "22nd Aug, 2015",
    "location": "EldoRado Park, Brampton",
    "description": "",
    "imageUrl": "",
    "upcoming": false
  },
  {
    "id": "7",
    "title": "Diwali Dine & Entertainment",
    "date": "5th Dec, 2015",
    "location": "Guru Mandir, Etobicoke",
    "description": "",
    "imageUrl": "",
    "upcoming": false
  },
  {
    "id": "8",
    "title": "Mataji Puja & Yagna",
    "date": "24th April, 2016",
    "location": "Bharat Sevashram Sangh",
    "description": "",
    "imageUrl": "",
    "upcoming": false
  },
  {
    "id": "9",
    "title": "Diwali Get Together",
    "date": "19th Nov, 2016",
    "location": "Sindhi Guru Mandir",
    "description": "",
    "imageUrl": "",
    "upcoming": false
  },
  {
    "id": "10",
    "title": "Mataji Puja & Yagna",
    "date": "14th May, 2017",
    "location": "Bharat Sevashram Sangh",
    "description": "",
    "imageUrl": "",
    "upcoming": false
  },
  {
    "id": "11",
    "title": "Picnic",
    "date": "19th Aug, 2017",
    "location": "EldoRado Park, Brampton",
    "description": "",
    "imageUrl": "",
    "upcoming": false
  },
  {
    "id": "12",
    "title": "Diwali Milan",
    "date": "18th Nov, 2017",
    "location": "Guru Mandir, Etobicoke",
    "description": "",
    "imageUrl": "",
    "upcoming": false
  },
  {
    "id": "13",
    "title": "Mataji Puja & Yagna",
    "date": "18th March, 2018",
    "location": "Bharat Sevashram Sangh",
    "description": "",
    "imageUrl": "",
    "upcoming": false
  },
  {
    "id": "14",
    "title": "Diwali Milan",
    "date": "18th Nov, 2018",
    "location": "Guru Mandir, Etobicoke",
    "description": "",
    "imageUrl": "",
    "upcoming": false
  },
  {
    "id": "15",
    "title": "Mataji Puja & Yagna",
    "date": "7th April, 2019",
    "location": "Bharat Sevashram Sangh",
    "description": "",
    "imageUrl": "",
    "upcoming": false
  },
  {
    "id": "16",
    "title": "Diwali & Gratitude Milan",
    "date": "22nd Nov, 2022",
    "location": "Sindhi Guru Mandir",
    "description": "",
    "imageUrl": "",
    "upcoming": false
  },
  {
    "id": "17",
    "title": "Picnic",
    "date": "15th July, 2023",
    "location": "1275 Mississauga Vly Blvd, Mississauga",
    "description": "",
    "imageUrl": "",
    "upcoming": false
  },
  {
    "id": "18",
    "title": "Garba",
    "date": "12th October, 2024",
    "location": "River Grove Community Center, Mississauga",
    "description": "",
    "imageUrl": "",
    "upcoming": false
  },
  {
    "id": "19",
    "title": "Mataji’s Havan 2025",
    "date": "5th April, 2025",
    "location": "Hindu Heritage Center, Mississauga",
    "description": "",
    "imageUrl": "",
    "upcoming": false
  },
  {
    "id": "20",
    "title": "Picnic",
    "date": "5th July, 2025",
    "location": "Lions Valley Park, Oakville",
    "description": "",
    "imageUrl": "",
    "upcoming": false
  },
  {
    "id": "21",
    "title": "Garba",
    "date": "28th September, 2025",
    "location": "Mississauga Valley Community Center",
    "description": "",
    "imageUrl": "",
    "upcoming": false
  }
]
